simplecel/__init__.py
simplecel/__main__.py
simplecel/api.py
simplecel/static/default.js
simplecel/static/favicon.ico
simplecel/static/index.css
simplecel/static/index.js
simplecel/static/renderer.js
simplecel/static/vendor/showdown.min.js
simplecel/static/vendor/showdown.min.js.map
simplecel/templates/index.html
simplecel/util.py
simplecel/views.py
simplecel-0.2.10.7.dist-info/entry_points.txt
simplecel-0.2.10.7.dist-info/LICENSE
simplecel-0.2.10.7.dist-info/WHEEL
simplecel-0.2.10.7.dist-info/METADATA
simplecel-0.2.10.7.dist-info/RECORD
